cista/__init__.py
cista/__main__.py
cista/_version.py
cista/api.py
cista/app.py
cista/auth.py
cista/config.py
cista/droppy.py
cista/fileio.py
cista/preview.py
cista/protocol.py
cista/serve.py
cista/server80.py
cista/session.py
cista/sso.py
cista/watching.py
cista/frontend-build/index.html
cista/frontend-build/robots.txt
cista/frontend-build/assets/icons-6j2UZ_HA.js
cista/frontend-build/assets/index-BHQJhxzY.js
cista/frontend-build/assets/index-De5UYAfC.css
cista/frontend-build/assets/logo-ctv8tVwU.svg
cista/frontend-build/assets/searchWorker-DbTcSX-c.js
cista/util/__init__.py
cista/util/apphelpers.py
cista/util/asynclink.py
cista/util/filename.py
cista/util/lrucache.py
cista/util/pwgen.py
cista-1.5.0.dist-info/METADATA
cista-1.5.0.dist-info/WHEEL
cista-1.5.0.dist-info/entry_points.txt
cista-1.5.0.dist-info/RECORD
