Metadata-Version: 2.4
Name: cista
Version: 1.5.0
Summary: Dropbox-like file server with modern web interface
Project-URL: Homepage, https://git.zi.fi/Vasanko/cista-storage
Author: Vasanko
Maintainer: Vasanko
Keywords: dropbox,file-server,storage,web-interface
Classifier: Development Status :: 5 - Production/Stable
Classifier: Environment :: Web Environment
Classifier: Intended Audience :: End Users/Desktop
Classifier: Intended Audience :: System Administrators
Classifier: License :: OSI Approved :: MIT License
Classifier: License :: Public Domain
Requires-Python: >=3.11
Requires-Dist: argon2-cffi>=25.1.0
Requires-Dist: av>=15.0.0
Requires-Dist: blake3>=1.0.5
Requires-Dist: docopt-ng>=0.9.0
Requires-Dist: fastapi-vue>=0.5.2
Requires-Dist: fastapi[standard]>=0.128.0
Requires-Dist: html5tagger>=1.3.0
Requires-Dist: httpx>=0.28.0
Requires-Dist: inotify>=0.2.12
Requires-Dist: msgspec>=0.19.0
Requires-Dist: natsort>=8.4.0
Requires-Dist: numpy>=2.3.2
Requires-Dist: pathvalidate>=3.3.1
Requires-Dist: pillow-heif>=1.1.0
Requires-Dist: pillow>=11.3.0
Requires-Dist: pyjwt>=2.10.1
Requires-Dist: pymupdf>=1.26.3
Requires-Dist: sanic>=25.12.0
Requires-Dist: setproctitle>=1.3.6
Requires-Dist: stream-zip>=0.0.83
Requires-Dist: tomli-w>=1.2.0
Requires-Dist: zstandard>=0.24.0
Provides-Extra: dev
Requires-Dist: mypy>=1.13.0; extra == 'dev'
Requires-Dist: pre-commit>=4.0.0; extra == 'dev'
Requires-Dist: pytest>=8.4.1; extra == 'dev'
Requires-Dist: ruff>=0.8.0; extra == 'dev'
Provides-Extra: docs
Requires-Dist: sphinx-rtd-theme>=3.0.0; extra == 'docs'
Requires-Dist: sphinx>=8.0.0; extra == 'docs'
Provides-Extra: test
Requires-Dist: pytest-asyncio>=0.25.0; extra == 'test'
Requires-Dist: pytest-cov>=6.0.0; extra == 'test'
Requires-Dist: pytest>=8.4.1; extra == 'test'
